powerhouse_assistant/__init__.py
powerhouse_assistant/Address_Book_Handler.py
powerhouse_assistant/addressbook.py
powerhouse_assistant/addressbook_data.py
powerhouse_assistant/AI_helper.py
powerhouse_assistant/GameGooseKiller/font/Candal.ttf
powerhouse_assistant/GameGooseKiller/Game_goose.py
powerhouse_assistant/GameGooseKiller/image/background/1-1.png
powerhouse_assistant/GameGooseKiller/image/background/1-2.png
powerhouse_assistant/GameGooseKiller/image/background/1-3.png
powerhouse_assistant/GameGooseKiller/image/background.png
powerhouse_assistant/GameGooseKiller/image/bonus.png
powerhouse_assistant/GameGooseKiller/image/boom.png
powerhouse_assistant/GameGooseKiller/image/box.png
powerhouse_assistant/GameGooseKiller/image/enemy.png
powerhouse_assistant/GameGooseKiller/image/Farm-Goose.ico
powerhouse_assistant/GameGooseKiller/image/gameover.png
powerhouse_assistant/GameGooseKiller/image/Goose/1-1.png
powerhouse_assistant/GameGooseKiller/image/Goose/1-2.png
powerhouse_assistant/GameGooseKiller/image/Goose/1-3.png
powerhouse_assistant/GameGooseKiller/image/Goose/1-4.png
powerhouse_assistant/GameGooseKiller/image/Goose/1-5.png
powerhouse_assistant/GameGooseKiller/image/heart.svg
powerhouse_assistant/GameGooseKiller/image/lifes/lifes_2.png
powerhouse_assistant/GameGooseKiller/image/lifes/lifes_3.png
powerhouse_assistant/main.py
powerhouse_assistant/Note.py
powerhouse_assistant/Note_Book_Handler.py
powerhouse_assistant/Snake.py
powerhouse_assistant/Sort_Files.py
powerhouse_assistant/Сalculator.py
powerhouse_helper-1.0.0.dist-info/entry_points.txt
powerhouse_helper-1.0.0.dist-info/METADATA
powerhouse_helper-1.0.0.dist-info/WHEEL
powerhouse_helper-1.0.0.dist-info/RECORD
